[
    {
        "id": 1,
        "first_name": "Berta",
        "last_name": "Rosell",
        "email": "brosell0@qq.com",
        "date_of_birth": "1996-02-19T03:17:38Z",
        "age": 46,
        "country": "Russia",
        "phone": "5377710217"
    },
    {
        "id": 2,
        "first_name": "Mirna",
        "last_name": "Rothert",
        "email": "mrothert1@wunderground.com",
        "date_of_birth": "1978-04-06T21:17:29Z",
        "age": 53,
        "country": "Russia",
        "phone": "5786241137"
    },
    {
        "id": 3,
        "first_name": "Archibaldo",
        "last_name": "Matschuk",
        "email": "amatschuk2@businessweek.com",
        "date_of_birth": "1984-04-09T23:27:24Z",
        "age": 48,
        "country": "Malaysia",
        "phone": "8508985740"
    },
    {
        "id": 4,
        "first_name": "Patricio",
        "last_name": "Crabb",
        "email": "pcrabb3@soundcloud.com",
        "date_of_birth": "1994-05-22T19:36:26Z",
        "age": 19,
        "country": "China",
        "phone": "2492233231"
    },
    {
        "id": 5,
        "first_name": "Mickey",
        "last_name": "Nisius",
        "email": "mnisius4@mysql.com",
        "date_of_birth": "1992-01-15T14:52:37Z",
        "age": 51,
        "country": "China",
        "phone": "4477190474"
    },
    {
        "id": 6,
        "first_name": "Maybelle",
        "last_name": "St. Hill",
        "email": "msthill5@blog.com",
        "date_of_birth": "1983-12-02T15:47:11Z",
        "age": 21,
        "country": "Ireland",
        "phone": "6422537917"
    },
    {
        "id": 7,
        "first_name": "Harlie",
        "last_name": "Gamell",
        "email": "hgamell6@forbes.com",
        "date_of_birth": "2015-12-06T06:27:02Z",
        "age": 19,
        "country": "Canada",
        "phone": "5225349674"
    },
    {
        "id": 8,
        "first_name": "Trix",
        "last_name": "Dogerty",
        "email": "tdogerty7@purevolume.com",
        "date_of_birth": "1980-03-22T03:34:11Z",
        "age": 39,
        "country": "China",
        "phone": "9781901441"
    },
    {
        "id": 9,
        "first_name": "Masha",
        "last_name": "Fentem",
        "email": "mfentem8@about.me",
        "date_of_birth": "1970-05-28T00:54:57Z",
        "age": 33,
        "country": "Syria",
        "phone": "7827344384"
    },
    {
        "id": 10,
        "first_name": "Delila",
        "last_name": "Keeting",
        "email": "dkeeting9@chron.com",
        "date_of_birth": "1980-06-11T13:19:39Z",
        "age": 49,
        "country": "Czech Republic",
        "phone": "9239447169"
    },
    {
        "id": 11,
        "first_name": "Niles",
        "last_name": "Clemmitt",
        "email": "nclemmitta@sohu.com",
        "date_of_birth": "2005-05-13T15:29:41Z",
        "age": 53,
        "country": "United States",
        "phone": "6267359342"
    },
    {
        "id": 12,
        "first_name": "Archie",
        "last_name": "Frye",
        "email": "afryeb@163.com",
        "date_of_birth": "1983-09-29T00:13:22Z",
        "age": 56,
        "country": "Russia",
        "phone": "9368009481"
    },
    {
        "id": 13,
        "first_name": "Marci",
        "last_name": "Wardhough",
        "email": "mwardhoughc@wisc.edu",
        "date_of_birth": "1970-02-03T02:51:05Z",
        "age": 44,
        "country": "Russia",
        "phone": "2565683999"
    },
    {
        "id": 14,
        "first_name": "Diego",
        "last_name": "McTiernan",
        "email": "dmctiernand@amazon.com",
        "date_of_birth": "1986-09-01T23:14:38Z",
        "age": 41,
        "country": "Mexico",
        "phone": "2124964363"
    },
    {
        "id": 15,
        "first_name": "Teodoor",
        "last_name": "Duker",
        "email": "tdukere@archive.org",
        "date_of_birth": "1996-07-04T08:36:07Z",
        "age": 19,
        "country": "Indonesia",
        "phone": "6559730668"
    },
    {
        "id": 16,
        "first_name": "Oates",
        "last_name": "Buckler",
        "email": "obucklerf@google.co.uk",
        "date_of_birth": "2010-09-01T18:26:31Z",
        "age": 26,
        "country": "Venezuela",
        "phone": "9239939841"
    },
    {
        "id": 17,
        "first_name": "Cassi",
        "last_name": "Burdon",
        "email": "cburdong@bloglovin.com",
        "date_of_birth": "1970-04-10T10:47:29Z",
        "age": 27,
        "country": "Nigeria",
        "phone": "8502241249"
    },
    {
        "id": 18,
        "first_name": "Nonah",
        "last_name": "Izhakov",
        "email": "nizhakovh@ycombinator.com",
        "date_of_birth": "1980-12-07T14:40:13Z",
        "age": 57,
        "country": "Venezuela",
        "phone": "8787079623"
    },
    {
        "id": 19,
        "first_name": "Dillon",
        "last_name": "Dadge",
        "email": "ddadgei@myspace.com",
        "date_of_birth": "2013-08-20T21:30:02Z",
        "age": 43,
        "country": "China",
        "phone": "4197326784"
    },
    {
        "id": 20,
        "first_name": "Dorthea",
        "last_name": "Basketter",
        "email": "dbasketterj@japanpost.jp",
        "date_of_birth": "1998-02-20T16:49:58Z",
        "age": 46,
        "country": "Australia",
        "phone": "7783394699"
    },
    {
        "id": 21,
        "first_name": "Torie",
        "last_name": "Topliss",
        "email": "ttoplissk@cocolog-nifty.com",
        "date_of_birth": "2000-05-10T21:28:44Z",
        "age": 47,
        "country": "Philippines",
        "phone": "4146292073"
    },
    {
        "id": 22,
        "first_name": "Ed",
        "last_name": "Grimditch",
        "email": "egrimditchl@slideshare.net",
        "date_of_birth": "1987-04-16T05:04:46Z",
        "age": 46,
        "country": "Russia",
        "phone": "2397658870"
    },
    {
        "id": 23,
        "first_name": "Alleyn",
        "last_name": "Headey",
        "email": "aheadeym@independent.co.uk",
        "date_of_birth": "1991-09-29T12:01:31Z",
        "age": 46,
        "country": "Yemen",
        "phone": "4977915963"
    },
    {
        "id": 24,
        "first_name": "Neely",
        "last_name": "Simonson",
        "email": "nsimonsonn@guardian.co.uk",
        "date_of_birth": "2019-04-17T19:39:54Z",
        "age": 50,
        "country": "Philippines",
        "phone": "9682727936"
    },
    {
        "id": 25,
        "first_name": "Bo",
        "last_name": "Scardefield",
        "email": "bscardefieldo@archive.org",
        "date_of_birth": "1987-11-05T05:13:22Z",
        "age": 52,
        "country": "Venezuela",
        "phone": "5346164775"
    },
    {
        "id": 26,
        "first_name": "Sidonnie",
        "last_name": "Bampton",
        "email": "sbamptonp@gov.uk",
        "date_of_birth": "2020-01-20T09:06:02Z",
        "age": 39,
        "country": "Philippines",
        "phone": "3601576538"
    },
    {
        "id": 27,
        "first_name": "Ailey",
        "last_name": "Leynagh",
        "email": "aleynaghq@youtube.com",
        "date_of_birth": "1970-05-14T19:54:36Z",
        "age": 21,
        "country": "China",
        "phone": "4135951803"
    },
    {
        "id": 28,
        "first_name": "Gypsy",
        "last_name": "Leare",
        "email": "glearer@wsj.com",
        "date_of_birth": "1972-05-19T19:37:33Z",
        "age": 38,
        "country": "Belarus",
        "phone": "4063395757"
    },
    {
        "id": 29,
        "first_name": "Francine",
        "last_name": "Arkow",
        "email": "farkows@woothemes.com",
        "date_of_birth": "1976-04-25T00:35:52Z",
        "age": 54,
        "country": "Bangladesh",
        "phone": "8632668546"
    },
    {
        "id": 30,
        "first_name": "Mortie",
        "last_name": "Corkell",
        "email": "mcorkellt@chronoengine.com",
        "date_of_birth": "1975-04-12T00:12:18Z",
        "age": 53,
        "country": "Russia",
        "phone": "1966055606"
    },
    {
        "id": 31,
        "first_name": "Odell",
        "last_name": "Oliffe",
        "email": "ooliffeu@tinyurl.com",
        "date_of_birth": "1986-09-05T11:20:40Z",
        "age": 25,
        "country": "Russia",
        "phone": "2655447874"
    },
    {
        "id": 32,
        "first_name": "Herb",
        "last_name": "Baillie",
        "email": "hbailliev@nymag.com",
        "date_of_birth": "1982-02-04T05:13:34Z",
        "age": 38,
        "country": "China",
        "phone": "2644368189"
    },
    {
        "id": 33,
        "first_name": "Pennie",
        "last_name": "Pietersma",
        "email": "ppietersmaw@sitemeter.com",
        "date_of_birth": "1988-09-29T00:26:13Z",
        "age": 43,
        "country": "Russia",
        "phone": "5667662292"
    },
    {
        "id": 34,
        "first_name": "Milissent",
        "last_name": "Abbys",
        "email": "mabbysx@nsw.gov.au",
        "date_of_birth": "1971-03-04T07:27:34Z",
        "age": 57,
        "country": "Philippines",
        "phone": "3827662412"
    },
    {
        "id": 35,
        "first_name": "Brietta",
        "last_name": "Woolhouse",
        "email": "bwoolhousey@webs.com",
        "date_of_birth": "2023-01-12T21:12:56Z",
        "age": 52,
        "country": "Czech Republic",
        "phone": "5977594442"
    },
    {
        "id": 36,
        "first_name": "Annabela",
        "last_name": "Iiannoni",
        "email": "aiiannoniz@privacy.gov.au",
        "date_of_birth": "1990-12-17T07:26:56Z",
        "age": 42,
        "country": "Poland",
        "phone": "1409705115"
    },
    {
        "id": 37,
        "first_name": "Hildy",
        "last_name": "Bramstom",
        "email": "hbramstom10@omniture.com",
        "date_of_birth": "1972-01-21T09:06:59Z",
        "age": 22,
        "country": "Mexico",
        "phone": "5842942054"
    },
    {
        "id": 38,
        "first_name": "Ado",
        "last_name": "Maha",
        "email": "amaha11@opera.com",
        "date_of_birth": "1970-09-11T05:13:39Z",
        "age": 29,
        "country": "Morocco",
        "phone": "3308016619"
    },
    {
        "id": 39,
        "first_name": "Wernher",
        "last_name": "Bielefeld",
        "email": "wbielefeld12@bravesites.com",
        "date_of_birth": "2008-03-05T00:04:54Z",
        "age": 35,
        "country": "Niger",
        "phone": "9544310441"
    },
    {
        "id": 40,
        "first_name": "Aubry",
        "last_name": "Bromilow",
        "email": "abromilow13@storify.com",
        "date_of_birth": "1985-03-01T09:42:20Z",
        "age": 33,
        "country": "Indonesia",
        "phone": "4786577432"
    },
    {
        "id": 41,
        "first_name": "Zelma",
        "last_name": "Cleghorn",
        "email": "zcleghorn14@jugem.jp",
        "date_of_birth": "1976-02-25T14:15:30Z",
        "age": 32,
        "country": "Gambia",
        "phone": "4009193293"
    },
    {
        "id": 42,
        "first_name": "Jerrold",
        "last_name": "Burnand",
        "email": "jburnand15@imgur.com",
        "date_of_birth": "1995-05-12T12:12:26Z",
        "age": 55,
        "country": "China",
        "phone": "5183041102"
    },
    {
        "id": 43,
        "first_name": "Ravi",
        "last_name": "Zannini",
        "email": "rzannini16@mtv.com",
        "date_of_birth": "1977-09-01T18:55:51Z",
        "age": 48,
        "country": "Mauritius",
        "phone": "3321072532"
    },
    {
        "id": 44,
        "first_name": "Sutherlan",
        "last_name": "Burniston",
        "email": "sburniston17@a8.net",
        "date_of_birth": "1999-01-31T00:02:35Z",
        "age": 32,
        "country": "Uganda",
        "phone": "6329218157"
    },
    {
        "id": 45,
        "first_name": "Anni",
        "last_name": "Khristoforov",
        "email": "akhristoforov18@wsj.com",
        "date_of_birth": "2001-01-06T07:22:00Z",
        "age": 29,
        "country": "Mexico",
        "phone": "2559505199"
    },
    {
        "id": 46,
        "first_name": "Tobye",
        "last_name": "Hanfrey",
        "email": "thanfrey19@php.net",
        "date_of_birth": "2014-05-20T17:46:07Z",
        "age": 23,
        "country": "Poland",
        "phone": "7683500849"
    },
    {
        "id": 47,
        "first_name": "Wally",
        "last_name": "Batterbee",
        "email": "wbatterbee1a@huffingtonpost.com",
        "date_of_birth": "2019-07-13T16:27:34Z",
        "age": 40,
        "country": "Malaysia",
        "phone": "9082879139"
    },
    {
        "id": 48,
        "first_name": "Michael",
        "last_name": "Calafate",
        "email": "mcalafate1b@ifeng.com",
        "date_of_birth": "2014-01-23T16:06:25Z",
        "age": 29,
        "country": "France",
        "phone": "9726526874"
    },
    {
        "id": 49,
        "first_name": "Mamie",
        "last_name": "Glowach",
        "email": "mglowach1c@google.co.uk",
        "date_of_birth": "1985-09-27T07:32:02Z",
        "age": 36,
        "country": "Russia",
        "phone": "2943966929"
    },
    {
        "id": 50,
        "first_name": "Federica",
        "last_name": "Rizzo",
        "email": "frizzo1d@elpais.com",
        "date_of_birth": "1972-02-17T10:22:09Z",
        "age": 37,
        "country": "China",
        "phone": "8105445236"
    },
    {
        "id": 51,
        "first_name": "Vinni",
        "last_name": "Hofler",
        "email": "vhofler1e@bandcamp.com",
        "date_of_birth": "2007-04-24T00:52:01Z",
        "age": 51,
        "country": "Poland",
        "phone": "7422075161"
    },
    {
        "id": 52,
        "first_name": "Kaitlynn",
        "last_name": "Towersey",
        "email": "ktowersey1f@desdev.cn",
        "date_of_birth": "2011-08-13T06:08:35Z",
        "age": 21,
        "country": "Norway",
        "phone": "3206844942"
    },
    {
        "id": 53,
        "first_name": "Olwen",
        "last_name": "Crippen",
        "email": "ocrippen1g@photobucket.com",
        "date_of_birth": "1995-07-18T15:22:37Z",
        "age": 31,
        "country": "Ecuador",
        "phone": "8692463214"
    },
    {
        "id": 54,
        "first_name": "Maddie",
        "last_name": "Kliner",
        "email": "mkliner1h@google.nl",
        "date_of_birth": "2013-09-13T00:22:17Z",
        "age": 41,
        "country": "Chile",
        "phone": "5645811873"
    },
    {
        "id": 55,
        "first_name": "Allyce",
        "last_name": "Redfearn",
        "email": "aredfearn1i@cnet.com",
        "date_of_birth": "1975-11-25T18:45:23Z",
        "age": 45,
        "country": "Indonesia",
        "phone": "1216820936"
    },
    {
        "id": 56,
        "first_name": "Adel",
        "last_name": "Lakes",
        "email": "alakes1j@virginia.edu",
        "date_of_birth": "2005-01-27T12:31:08Z",
        "age": 25,
        "country": "Madagascar",
        "phone": "3347000602"
    },
    {
        "id": 57,
        "first_name": "Jamey",
        "last_name": "Fancy",
        "email": "jfancy1k@google.com.br",
        "date_of_birth": "1970-08-19T09:47:49Z",
        "age": 35,
        "country": "China",
        "phone": "6557038278"
    },
    {
        "id": 58,
        "first_name": "Anissa",
        "last_name": "O'Hearn",
        "email": "aohearn1l@miibeian.gov.cn",
        "date_of_birth": "2004-10-17T18:07:22Z",
        "age": 52,
        "country": "Botswana",
        "phone": "7184367813"
    },
    {
        "id": 59,
        "first_name": "Dame",
        "last_name": "Courtenay",
        "email": "dcourtenay1m@princeton.edu",
        "date_of_birth": "1970-01-19T14:59:10Z",
        "age": 32,
        "country": "Brazil",
        "phone": "4513045762"
    },
    {
        "id": 60,
        "first_name": "Henri",
        "last_name": "Spurier",
        "email": "hspurier1n@yale.edu",
        "date_of_birth": "2018-12-12T07:39:15Z",
        "age": 27,
        "country": "Brazil",
        "phone": "7137318312"
    },
    {
        "id": 61,
        "first_name": "Remington",
        "last_name": "Wheater",
        "email": "rwheater1o@quantcast.com",
        "date_of_birth": "2011-06-06T14:51:31Z",
        "age": 22,
        "country": "Belarus",
        "phone": "6436106116"
    },
    {
        "id": 62,
        "first_name": "Barnie",
        "last_name": "Anthill",
        "email": "banthill1p@boston.com",
        "date_of_birth": "2023-04-19T15:09:06Z",
        "age": 29,
        "country": "Mongolia",
        "phone": "1685982095"
    },
    {
        "id": 63,
        "first_name": "Kellby",
        "last_name": "Lattey",
        "email": "klattey1q@newsvine.com",
        "date_of_birth": "1985-05-08T10:01:02Z",
        "age": 19,
        "country": "Cyprus",
        "phone": "5781572202"
    },
    {
        "id": 64,
        "first_name": "Malory",
        "last_name": "Vassall",
        "email": "mvassall1r@canalblog.com",
        "date_of_birth": "1970-10-16T06:58:04Z",
        "age": 45,
        "country": "China",
        "phone": "4818787060"
    },
    {
        "id": 65,
        "first_name": "Cazzie",
        "last_name": "O'Collopy",
        "email": "cocollopy1s@narod.ru",
        "date_of_birth": "1982-05-09T11:46:31Z",
        "age": 35,
        "country": "Russia",
        "phone": "8389291814"
    },
    {
        "id": 66,
        "first_name": "Cindra",
        "last_name": "Camilleri",
        "email": "ccamilleri1t@uol.com.br",
        "date_of_birth": "1971-10-14T22:20:10Z",
        "age": 21,
        "country": "Aruba",
        "phone": "4303562095"
    },
    {
        "id": 67,
        "first_name": "Othilia",
        "last_name": "Ridpath",
        "email": "oridpath1u@webs.com",
        "date_of_birth": "1982-05-09T17:24:37Z",
        "age": 29,
        "country": "Portugal",
        "phone": "6417723207"
    },
    {
        "id": 68,
        "first_name": "Britni",
        "last_name": "Stevens",
        "email": "bstevens1v@webmd.com",
        "date_of_birth": "1982-11-02T14:50:58Z",
        "age": 35,
        "country": "Portugal",
        "phone": "1759771468"
    },
    {
        "id": 69,
        "first_name": "Donni",
        "last_name": "Jouannisson",
        "email": "djouannisson1w@ihg.com",
        "date_of_birth": "1985-05-21T05:02:19Z",
        "age": 46,
        "country": "Sweden",
        "phone": "6497467222"
    },
    {
        "id": 70,
        "first_name": "Dara",
        "last_name": "Mallindine",
        "email": "dmallindine1x@github.com",
        "date_of_birth": "2000-04-28T23:23:05Z",
        "age": 54,
        "country": "Portugal",
        "phone": "5936913617"
    },
    {
        "id": 71,
        "first_name": "Tyson",
        "last_name": "Hartas",
        "email": "thartas1y@addtoany.com",
        "date_of_birth": "1975-12-29T21:37:41Z",
        "age": 32,
        "country": "Maldives",
        "phone": "5379205708"
    },
    {
        "id": 72,
        "first_name": "Herb",
        "last_name": "Bosanko",
        "email": "hbosanko1z@china.com.cn",
        "date_of_birth": "1987-04-16T18:21:50Z",
        "age": 43,
        "country": "Indonesia",
        "phone": "1001160355"
    },
    {
        "id": 73,
        "first_name": "Kipp",
        "last_name": "Hissett",
        "email": "khissett20@npr.org",
        "date_of_birth": "1970-06-19T11:01:43Z",
        "age": 43,
        "country": "Poland",
        "phone": "2679424647"
    },
    {
        "id": 74,
        "first_name": "Hanny",
        "last_name": "Daniel",
        "email": "hdaniel21@wix.com",
        "date_of_birth": "1982-02-02T02:22:19Z",
        "age": 31,
        "country": "France",
        "phone": "4904853060"
    },
    {
        "id": 75,
        "first_name": "Grier",
        "last_name": "Tother",
        "email": "gtother22@dedecms.com",
        "date_of_birth": "1996-01-20T13:37:37Z",
        "age": 23,
        "country": "China",
        "phone": "8519434110"
    },
    {
        "id": 76,
        "first_name": "Herold",
        "last_name": "Laurenson",
        "email": "hlaurenson23@whitehouse.gov",
        "date_of_birth": "2015-01-31T19:46:13Z",
        "age": 51,
        "country": "Indonesia",
        "phone": "3013635415"
    },
    {
        "id": 77,
        "first_name": "Pip",
        "last_name": "Hindrich",
        "email": "phindrich24@columbia.edu",
        "date_of_birth": "1974-05-17T23:03:04Z",
        "age": 25,
        "country": "China",
        "phone": "4713102732"
    },
    {
        "id": 78,
        "first_name": "Yehudit",
        "last_name": "Ffoulkes",
        "email": "yffoulkes25@wordpress.org",
        "date_of_birth": "1987-11-09T05:54:54Z",
        "age": 26,
        "country": "Canada",
        "phone": "6606714403"
    },
    {
        "id": 79,
        "first_name": "Phaedra",
        "last_name": "Paolazzi",
        "email": "ppaolazzi26@naver.com",
        "date_of_birth": "1979-06-20T17:21:21Z",
        "age": 22,
        "country": "United States",
        "phone": "3191368020"
    },
    {
        "id": 80,
        "first_name": "Jody",
        "last_name": "Abrehart",
        "email": "jabrehart27@nydailynews.com",
        "date_of_birth": "1999-04-19T11:45:14Z",
        "age": 39,
        "country": "Pakistan",
        "phone": "4713432489"
    },
    {
        "id": 81,
        "first_name": "Sarge",
        "last_name": "Rydzynski",
        "email": "srydzynski28@psu.edu",
        "date_of_birth": "2017-08-08T06:33:29Z",
        "age": 54,
        "country": "United Arab Emirates",
        "phone": "4345955598"
    },
    {
        "id": 82,
        "first_name": "Georgetta",
        "last_name": "Coetzee",
        "email": "gcoetzee29@boston.com",
        "date_of_birth": "2021-03-16T03:20:49Z",
        "age": 34,
        "country": "Brazil",
        "phone": "3928383825"
    },
    {
        "id": 83,
        "first_name": "Hephzibah",
        "last_name": "Sorrel",
        "email": "hsorrel2a@army.mil",
        "date_of_birth": "1994-11-13T08:01:51Z",
        "age": 38,
        "country": "China",
        "phone": "8864098949"
    },
    {
        "id": 84,
        "first_name": "Etta",
        "last_name": "Doddemeede",
        "email": "edoddemeede2b@amazon.com",
        "date_of_birth": "1995-10-31T15:32:05Z",
        "age": 43,
        "country": "Philippines",
        "phone": "2753866985"
    },
    {
        "id": 85,
        "first_name": "Selie",
        "last_name": "Chantree",
        "email": "schantree2c@mapy.cz",
        "date_of_birth": "1972-11-13T23:00:23Z",
        "age": 57,
        "country": "Indonesia",
        "phone": "3292567004"
    },
    {
        "id": 86,
        "first_name": "Ariella",
        "last_name": "Frankes",
        "email": "afrankes2d@hugedomains.com",
        "date_of_birth": "1978-12-23T20:49:46Z",
        "age": 19,
        "country": "Zambia",
        "phone": "3155915988"
    },
    {
        "id": 87,
        "first_name": "Maxwell",
        "last_name": "Laister",
        "email": "mlaister2e@reverbnation.com",
        "date_of_birth": "1976-12-06T14:44:47Z",
        "age": 50,
        "country": "China",
        "phone": "4308122615"
    },
    {
        "id": 88,
        "first_name": "Carmelita",
        "last_name": "Merrigan",
        "email": "cmerrigan2f@simplemachines.org",
        "date_of_birth": "2023-03-06T22:29:47Z",
        "age": 54,
        "country": "Russia",
        "phone": "1833452237"
    },
    {
        "id": 89,
        "first_name": "Abbot",
        "last_name": "Yard",
        "email": "ayard2g@java.com",
        "date_of_birth": "2001-08-22T22:06:23Z",
        "age": 30,
        "country": "Indonesia",
        "phone": "3472386037"
    },
    {
        "id": 90,
        "first_name": "Vikki",
        "last_name": "Kleen",
        "email": "vkleen2h@amazon.co.jp",
        "date_of_birth": "1979-04-08T23:19:31Z",
        "age": 56,
        "country": "Iraq",
        "phone": "2116932578"
    },
    {
        "id": 91,
        "first_name": "Vere",
        "last_name": "Broomer",
        "email": "vbroomer2i@mit.edu",
        "date_of_birth": "2001-07-13T19:34:31Z",
        "age": 41,
        "country": "Venezuela",
        "phone": "2092729808"
    },
    {
        "id": 92,
        "first_name": "Townsend",
        "last_name": "Domenico",
        "email": "tdomenico2j@soundcloud.com",
        "date_of_birth": "1978-10-28T01:32:34Z",
        "age": 54,
        "country": "Canada",
        "phone": "4253855472"
    },
    {
        "id": 93,
        "first_name": "Jory",
        "last_name": "Dassindale",
        "email": "jdassindale2k@jiathis.com",
        "date_of_birth": "1980-07-18T00:02:38Z",
        "age": 45,
        "country": "France",
        "phone": "6445052523"
    },
    {
        "id": 94,
        "first_name": "Barnebas",
        "last_name": "Gresham",
        "email": "bgresham2l@statcounter.com",
        "date_of_birth": "2006-10-09T19:25:20Z",
        "age": 39,
        "country": "Canada",
        "phone": "4293203392"
    },
    {
        "id": 95,
        "first_name": "Lewes",
        "last_name": "Clapton",
        "email": "lclapton2m@cbslocal.com",
        "date_of_birth": "1997-08-16T15:11:27Z",
        "age": 35,
        "country": "Philippines",
        "phone": "8319228775"
    },
    {
        "id": 96,
        "first_name": "Corena",
        "last_name": "Boddis",
        "email": "cboddis2n@businessweek.com",
        "date_of_birth": "1971-02-06T02:32:18Z",
        "age": 37,
        "country": "China",
        "phone": "9691569959"
    },
    {
        "id": 97,
        "first_name": "Danya",
        "last_name": "Mitten",
        "email": "dmitten2o@fema.gov",
        "date_of_birth": "1999-04-21T19:18:23Z",
        "age": 26,
        "country": "China",
        "phone": "6064071946"
    },
    {
        "id": 98,
        "first_name": "Brinn",
        "last_name": "Kenrat",
        "email": "bkenrat2p@statcounter.com",
        "date_of_birth": "1989-05-22T05:53:40Z",
        "age": 46,
        "country": "Netherlands",
        "phone": "5274828355"
    },
    {
        "id": 99,
        "first_name": "Larina",
        "last_name": "Redmond",
        "email": "lredmond2q@simplemachines.org",
        "date_of_birth": "1979-09-23T16:32:39Z",
        "age": 50,
        "country": "Indonesia",
        "phone": "4038030937"
    },
    {
        "id": 100,
        "first_name": "Stormie",
        "last_name": "Vannuchi",
        "email": "svannuchi2r@census.gov",
        "date_of_birth": "1987-12-20T04:21:16Z",
        "age": 33,
        "country": "Philippines",
        "phone": "3987481444"
    }
]